cardaio/__init__.py
cardaio/_core.py
cardaio/py.typed
cardaio-1.0.0.dist-info/LICENSE
cardaio-1.0.0.dist-info/WHEEL
cardaio-1.0.0.dist-info/METADATA
cardaio-1.0.0.dist-info/RECORD
